[
    {
        "time": 187,
        "type": "word",
        "start": 28,
        "end": 29,
        "value": "3"
    },
    {
        "time": 1301,
        "type": "word",
        "start": 31,
        "end": 36,
        "value": "Sugar"
    },
    {
        "time": 1668,
        "type": "word",
        "start": 37,
        "end": 40,
        "value": "was"
    },
    {
        "time": 2050,
        "type": "word",
        "start": 41,
        "end": 43,
        "value": "on"
    },
    {
        "time": 2172,
        "type": "word",
        "start": 44,
        "end": 45,
        "value": "a"
    },
    {
        "time": 2279,
        "type": "word",
        "start": 46,
        "end": 49,
        "value": "mat"
    }
]