[
    {
        "time": 137,
        "type": "word",
        "start": 28,
        "end": 32,
        "value": "It's"
    },
    {
        "time": 351,
        "type": "word",
        "start": 33,
        "end": 38,
        "value": "rainy"
    },
    {
        "time": 733,
        "type": "word",
        "start": 39,
        "end": 42,
        "value": "now"
    },
    {
        "time": 1824,
        "type": "word",
        "start": 44,
        "end": 47,
        "value": "How"
    },
    {
        "time": 2053,
        "type": "word",
        "start": 48,
        "end": 50,
        "value": "do"
    },
    {
        "time": 2129,
        "type": "word",
        "start": 51,
        "end": 54,
        "value": "you"
    },
    {
        "time": 2267,
        "type": "word",
        "start": 55,
        "end": 59,
        "value": "feel"
    }
]