{
    "0": {
        "text": "For free distribution 19",
        "words": [
            "For",
            "free",
            "distribution",
            "19"
        ],
        "bounding_boxes": [
            [
                [
                    309.4750061035156,
                    644.4630737304688
                ],
                [
                    325.0828857421875,
                    659.049072265625
                ]
            ],
            [
                [
                    327.5028991699219,
                    644.4630737304688
                ],
                [
                    345.14910888671875,
                    659.049072265625
                ]
            ],
            [
                [
                    347.5691223144531,
                    644.4630737304688
                ],
                [
                    401.62310791015625,
                    659.049072265625
                ]
            ],
            [
                [
                    423.6600036621094,
                    640.7908935546875
                ],
                [
                    435.6600036621094,
                    656.7869262695312
                ]
            ]
        ]
    },
    "1": {
        "text": "7. I had a glass of hot water. 8. The concert ended around 8 p.m. 9. The big house he bought was expensive. 10. Rumali has long hair.",
        "words": [
            "7.",
            "I",
            "had",
            "a",
            "glass",
            "of",
            "hot",
            "water.",
            "8.",
            "The",
            "concert",
            "ended",
            "around",
            "8",
            "p.m.",
            "9.",
            "The",
            "big",
            "house",
            "he",
            "bought",
            "was",
            "expensive.",
            "10.",
            "Rumali",
            "has",
            "long",
            "hair."
        ],
        "bounding_boxes": [
            [
                [
                    108.75,
                    49.922672271728516
                ],
                [
                    118.5,
                    67.00466918945312
                ]
            ],
            [
                [
                    125.0,
                    49.922672271728516
                ],
                [
                    129.32899475097656,
                    67.00466918945312
                ]
            ],
            [
                [
                    132.57899475097656,
                    49.922672271728516
                ],
                [
                    151.3509979248047,
                    67.00466918945312
                ]
            ],
            [
                [
                    154.6009979248047,
                    49.922672271728516
                ],
                [
                    160.3730010986328,
                    67.00466918945312
                ]
            ],
            [
                [
                    163.6230010986328,
                    49.922672271728516
                ],
                [
                    189.62301635742188,
                    67.00466918945312
                ]
            ],
            [
                [
                    192.87301635742188,
                    49.922672271728516
                ],
                [
                    203.70201110839844,
                    67.00466918945312
                ]
            ],
            [
                [
                    206.95201110839844,
                    49.922672271728516
                ],
                [
                    223.56600952148438,
                    67.00466918945312
                ]
            ],
            [
                [
                    226.81600952148438,
                    49.922672271728516
                ],
                [
                    258.21881103515625,
                    67.00466918945312
                ]
            ],
            [
                [
                    108.75,
                    65.52264404296875
                ],
                [
                    118.5,
                    82.60464477539062
                ]
            ],
            [
                [
                    124.76470184326172,
                    65.52264404296875
                ],
                [
                    144.97970581054688,
                    82.60464477539062
                ]
            ],
            [
                [
                    148.22970581054688,
                    65.52264404296875
                ],
                [
                    186.48870849609375,
                    82.60464477539062
                ]
            ],
            [
                [
                    189.7270050048828,
                    65.52264404296875
                ],
                [
                    220.77101135253906,
                    82.60464477539062
                ]
            ],
            [
                [
                    227.27101135253906,
                    65.52264404296875
                ],
                [
                    263.37200927734375,
                    82.60464477539062
                ]
            ],
            [
                [
                    266.62200927734375,
                    65.52264404296875
                ],
                [
                    273.12200927734375,
                    82.60464477539062
                ]
            ],
            [
                [
                    276.37200927734375,
                    65.52264404296875
                ],
                [
                    299.48602294921875,
                    82.60464477539062
                ]
            ],
            [
                [
                    108.75,
                    81.12261962890625
                ],
                [
                    118.5,
                    98.20462036132812
                ]
            ],
            [
                [
                    124.76470184326172,
                    81.12261962890625
                ],
                [
                    144.97970581054688,
                    98.20462036132812
                ]
            ],
            [
                [
                    148.22970581054688,
                    81.12261962890625
                ],
                [
                    164.8437042236328,
                    98.20462036132812
                ]
            ],
            [
                [
                    168.0937042236328,
                    81.12261962890625
                ],
                [
                    198.42271423339844,
                    98.20462036132812
                ]
            ],
            [
                [
                    201.67271423339844,
                    81.12261962890625
                ],
                [
                    213.94471740722656,
                    98.20462036132812
                ]
            ],
            [
                [
                    217.19471740722656,
                    81.12261962890625
                ],
                [
                    253.3087158203125,
                    98.20462036132812
                ]
            ],
            [
                [
                    256.5587158203125,
                    81.12261962890625
                ],
                [
                    276.7737121582031,
                    98.20462036132812
                ]
            ],
            [
                [
                    280.0119934082031,
                    81.12261962890625
                ],
                [
                    335.2489929199219,
                    98.20462036132812
                ]
            ],
            [
                [
                    105.5,
                    96.72259521484375
                ],
                [
                    121.75,
                    113.80459594726562
                ]
            ],
            [
                [
                    125.0,
                    96.72259521484375
                ],
                [
                    163.28500366210938,
                    113.80459594726562
                ]
            ],
            [
                [
                    166.53500366210938,
                    96.72259521484375
                ],
                [
                    183.864013671875,
                    113.80459594726562
                ]
            ],
            [
                [
                    187.10101318359375,
                    96.72259521484375
                ],
                [
                    210.2150115966797,
                    113.80459594726562
                ]
            ],
            [
                [
                    213.4650115966797,
                    96.72259521484375
                ],
                [
                    236.20980834960938,
                    113.80459594726562
                ]
            ]
        ]
    },
    "2": {
        "text": "Using the apostrophe We use an apostrophe to; 1) \u2022 Show the omission of a letter (contraction) \u2013 positive I am \u2013 I\u2019m Who is \u2013 Who\u2019s You are \u2013 You\u2019re Here is \u2013 Here\u2019s He is \u2013 He\u2019s Let us- Let\u2019s She is \u2013 She\u2019s That is \u2013 That\u2019s It is \u2013 It\u2019s There is \u2013 There\u2019s We are \u2013 We\u2019re They are \u2013 They\u2019re",
        "words": [
            "Using",
            "the",
            "apostrophe",
            "We",
            "use",
            "an",
            "apostrophe",
            "to;",
            "1)",
            "\u2022",
            "Show",
            "the",
            "omission",
            "of",
            "a",
            "letter",
            "(contraction)",
            "\u2013",
            "positive",
            "I",
            "am",
            "\u2013",
            "I\u2019m",
            "Who",
            "is",
            "\u2013",
            "Who\u2019s",
            "You",
            "are",
            "\u2013",
            "You\u2019re",
            "Here",
            "is",
            "\u2013",
            "Here\u2019s",
            "He",
            "is",
            "\u2013",
            "He\u2019s",
            "Let",
            "us-",
            "Let\u2019s",
            "She",
            "is",
            "\u2013",
            "She\u2019s",
            "That",
            "is",
            "\u2013",
            "That\u2019s",
            "It",
            "is",
            "\u2013",
            "It\u2019s",
            "There",
            "is",
            "\u2013",
            "There\u2019s",
            "We",
            "are",
            "\u2013",
            "We\u2019re",
            "They",
            "are",
            "\u2013",
            "They\u2019re"
        ],
        "bounding_boxes": [
            [
                [
                    203.22999572753906,
                    127.18373107910156
                ],
                [
                    237.45999145507812,
                    145.84573364257812
                ]
            ],
            [
                [
                    240.95999145507812,
                    127.18373107910156
                ],
                [
                    259.6219787597656,
                    145.84573364257812
                ]
            ],
            [
                [
                    263.1219787597656,
                    127.18373107910156
                ],
                [
                    329.767578125,
                    145.84573364257812
                ]
            ],
            [
                [
                    74.0,
                    144.05670166015625
                ],
                [
                    91.00140380859375,
                    161.13870239257812
                ]
            ],
            [
                [
                    94.25140380859375,
                    144.05670166015625
                ],
                [
                    111.58040618896484,
                    161.13870239257812
                ]
            ],
            [
                [
                    114.83040618896484,
                    144.05670166015625
                ],
                [
                    127.10240936279297,
                    161.13870239257812
                ]
            ],
            [
                [
                    130.3524169921875,
                    144.05670166015625
                ],
                [
                    187.39642333984375,
                    161.13870239257812
                ]
            ],
            [
                [
                    190.64642333984375,
                    144.05670166015625
                ],
                [
                    204.37442016601562,
                    161.13870239257812
                ]
            ],
            [
                [
                    72.9990005493164,
                    159.65670776367188
                ],
                [
                    83.8280029296875,
                    176.73870849609375
                ]
            ],
            [
                [
                    87.0780029296875,
                    159.65670776367188
                ],
                [
                    91.62800598144531,
                    176.73870849609375
                ]
            ],
            [
                [
                    93.99400329589844,
                    159.65670776367188
                ],
                [
                    123.60800170898438,
                    176.73870849609375
                ]
            ],
            [
                [
                    126.85800170898438,
                    159.65670776367188
                ],
                [
                    142.74400329589844,
                    176.73870849609375
                ]
            ],
            [
                [
                    145.99400329589844,
                    159.65670776367188
                ],
                [
                    192.95001220703125,
                    176.73870849609375
                ]
            ],
            [
                [
                    196.20001220703125,
                    159.65670776367188
                ],
                [
                    207.0290069580078,
                    176.73870849609375
                ]
            ],
            [
                [
                    210.2790069580078,
                    159.65670776367188
                ],
                [
                    216.05101013183594,
                    176.73870849609375
                ]
            ],
            [
                [
                    219.30101013183594,
                    159.65670776367188
                ],
                [
                    246.01600646972656,
                    176.73870849609375
                ]
            ],
            [
                [
                    249.26600646972656,
                    159.65670776367188
                ],
                [
                    316.41107177734375,
                    176.73870849609375
                ]
            ],
            [
                [
                    319.66107177734375,
                    159.65670776367188
                ],
                [
                    326.16107177734375,
                    176.73870849609375
                ]
            ],
            [
                [
                    329.41107177734375,
                    159.65670776367188
                ],
                [
                    370.5821228027344,
                    176.73870849609375
                ]
            ],
            [
                [
                    93.99400329589844,
                    175.2567138671875
                ],
                [
                    98.32300567626953,
                    192.33871459960938
                ]
            ],
            [
                [
                    101.57300567626953,
                    175.2567138671875
                ],
                [
                    117.4590072631836,
                    192.33871459960938
                ]
            ],
            [
                [
                    120.7090072631836,
                    175.2567138671875
                ],
                [
                    127.2090072631836,
                    192.33871459960938
                ]
            ],
            [
                [
                    130.45901489257812,
                    175.2567138671875
                ],
                [
                    149.2310028076172,
                    192.33871459960938
                ]
            ],
            [
                [
                    252.99700927734375,
                    175.2567138671875
                ],
                [
                    278.2690124511719,
                    192.33871459960938
                ]
            ],
            [
                [
                    281.5190124511719,
                    175.2567138671875
                ],
                [
                    290.1900329589844,
                    192.33871459960938
                ]
            ],
            [
                [
                    293.4400329589844,
                    175.2567138671875
                ],
                [
                    299.9400329589844,
                    192.33871459960938
                ]
            ],
            [
                [
                    302.95343017578125,
                    175.2567138671875
                ],
                [
                    336.8925476074219,
                    192.33871459960938
                ]
            ],
            [
                [
                    93.99401092529297,
                    190.85671997070312
                ],
                [
                    115.08131408691406,
                    207.938720703125
                ]
            ],
            [
                [
                    118.33131408691406,
                    190.85671997070312
                ],
                [
                    134.20431518554688,
                    207.938720703125
                ]
            ],
            [
                [
                    137.45431518554688,
                    190.85671997070312
                ],
                [
                    143.95431518554688,
                    207.938720703125
                ]
            ],
            [
                [
                    146.71810913085938,
                    190.85671997070312
                ],
                [
                    182.23410034179688,
                    207.938720703125
                ]
            ],
            [
                [
                    252.99700927734375,
                    190.85671997070312
                ],
                [
                    278.2560119628906,
                    207.938720703125
                ]
            ],
            [
                [
                    281.5060119628906,
                    190.85671997070312
                ],
                [
                    290.1770324707031,
                    207.938720703125
                ]
            ],
            [
                [
                    293.4270324707031,
                    190.85671997070312
                ],
                [
                    299.9270324707031,
                    207.938720703125
                ]
            ],
            [
                [
                    303.1770324707031,
                    190.85671997070312
                ],
                [
                    337.1018371582031,
                    207.938720703125
                ]
            ],
            [
                [
                    93.99401092529297,
                    206.45672607421875
                ],
                [
                    109.15201568603516,
                    223.53872680664062
                ]
            ],
            [
                [
                    112.40201568603516,
                    206.45672607421875
                ],
                [
                    121.07301330566406,
                    223.53872680664062
                ]
            ],
            [
                [
                    124.32301330566406,
                    206.45672607421875
                ],
                [
                    130.82301330566406,
                    223.53872680664062
                ]
            ],
            [
                [
                    134.07301330566406,
                    206.45672607421875
                ],
                [
                    157.90072631835938,
                    223.53872680664062
                ]
            ],
            [
                [
                    252.99700927734375,
                    206.45672607421875
                ],
                [
                    270.3260192871094,
                    223.53872680664062
                ]
            ],
            [
                [
                    273.5760192871094,
                    206.45672607421875
                ],
                [
                    289.4620361328125,
                    223.53872680664062
                ]
            ],
            [
                [
                    292.7120361328125,
                    206.45672607421875
                ],
                [
                    318.6990661621094,
                    223.53872680664062
                ]
            ],
            [
                [
                    93.99401092529297,
                    222.05673217773438
                ],
                [
                    113.4940185546875,
                    239.13873291015625
                ]
            ],
            [
                [
                    116.7440185546875,
                    222.05673217773438
                ],
                [
                    125.4150161743164,
                    239.13873291015625
                ]
            ],
            [
                [
                    128.66500854492188,
                    222.05673217773438
                ],
                [
                    135.16500854492188,
                    239.13873291015625
                ]
            ],
            [
                [
                    138.41500854492188,
                    222.05673217773438
                ],
                [
                    166.58340454101562,
                    239.13873291015625
                ]
            ],
            [
                [
                    252.99700927734375,
                    222.05673217773438
                ],
                [
                    276.8260192871094,
                    239.13873291015625
                ]
            ],
            [
                [
                    280.0760192871094,
                    222.05673217773438
                ],
                [
                    288.7470397949219,
                    239.13873291015625
                ]
            ],
            [
                [
                    291.9970397949219,
                    222.05673217773438
                ],
                [
                    298.4970397949219,
                    239.13873291015625
                ]
            ],
            [
                [
                    301.50653076171875,
                    222.05673217773438
                ],
                [
                    333.9974670410156,
                    239.13873291015625
                ]
            ],
            [
                [
                    93.99401092529297,
                    237.65673828125
                ],
                [
                    101.93701171875,
                    254.73873901367188
                ]
            ],
            [
                [
                    105.18701171875,
                    237.65673828125
                ],
                [
                    113.8580093383789,
                    254.73873901367188
                ]
            ],
            [
                [
                    117.1080093383789,
                    237.65673828125
                ],
                [
                    123.6080093383789,
                    254.73873901367188
                ]
            ],
            [
                [
                    126.8580093383789,
                    237.65673828125
                ],
                [
                    143.46551513671875,
                    254.73873901367188
                ]
            ],
            [
                [
                    252.99700927734375,
                    237.65673828125
                ],
                [
                    283.3130187988281,
                    254.73873901367188
                ]
            ],
            [
                [
                    286.5630187988281,
                    237.65673828125
                ],
                [
                    295.2340393066406,
                    254.73873901367188
                ]
            ],
            [
                [
                    298.4840393066406,
                    237.65673828125
                ],
                [
                    304.9840393066406,
                    254.73873901367188
                ]
            ],
            [
                [
                    307.9935302734375,
                    237.65673828125
                ],
                [
                    346.9714660644531,
                    254.73873901367188
                ]
            ],
            [
                [
                    93.99401092529297,
                    253.25674438476562
                ],
                [
                    110.99541473388672,
                    270.3387451171875
                ]
            ],
            [
                [
                    114.24541473388672,
                    253.25674438476562
                ],
                [
                    130.11842346191406,
                    270.3387451171875
                ]
            ],
            [
                [
                    133.36842346191406,
                    253.25674438476562
                ],
                [
                    139.86842346191406,
                    270.3387451171875
                ]
            ],
            [
                [
                    142.8779296875,
                    253.25674438476562
                ],
                [
                    174.3080291748047,
                    270.3387451171875
                ]
            ],
            [
                [
                    252.99700927734375,
                    253.25674438476562
                ],
                [
                    279.7120056152344,
                    270.3387451171875
                ]
            ],
            [
                [
                    282.9620056152344,
                    253.25674438476562
                ],
                [
                    298.83502197265625,
                    270.3387451171875
                ]
            ],
            [
                [
                    302.08502197265625,
                    253.25674438476562
                ],
                [
                    308.58502197265625,
                    270.3387451171875
                ]
            ],
            [
                [
                    311.5919189453125,
                    253.25674438476562
                ],
                [
                    352.7369384765625,
                    270.3387451171875
                ]
            ]
        ]
    },
    "3": {
        "text": "\u2022 Show the omission of a letter (contraction) \u2013 negative + question Are not \u2013 Aren\u2019t Is not \u2013 Isn\u2019t Do not \u2013 Don\u2019t Should not \u2013 Shouldn\u2019t",
        "words": [
            "\u2022",
            "Show",
            "the",
            "omission",
            "of",
            "a",
            "letter",
            "(contraction)",
            "\u2013",
            "negative",
            "+",
            "question",
            "Are",
            "not",
            "\u2013",
            "Aren\u2019t",
            "Is",
            "not",
            "\u2013",
            "Isn\u2019t",
            "Do",
            "not",
            "\u2013",
            "Don\u2019t",
            "Should",
            "not",
            "\u2013",
            "Shouldn\u2019t"
        ],
        "bounding_boxes": [
            [
                [
                    82.74900817871094,
                    275.8507385253906
                ],
                [
                    87.29901123046875,
                    292.9327392578125
                ]
            ],
            [
                [
                    93.99401092529297,
                    275.8507385253906
                ],
                [
                    123.60801696777344,
                    292.9327392578125
                ]
            ],
            [
                [
                    126.85801696777344,
                    275.8507385253906
                ],
                [
                    142.7440185546875,
                    292.9327392578125
                ]
            ],
            [
                [
                    145.9940185546875,
                    275.8507385253906
                ],
                [
                    192.9500274658203,
                    292.9327392578125
                ]
            ],
            [
                [
                    196.2000274658203,
                    275.8507385253906
                ],
                [
                    207.02902221679688,
                    292.9327392578125
                ]
            ],
            [
                [
                    210.27902221679688,
                    275.8507385253906
                ],
                [
                    216.051025390625,
                    292.9327392578125
                ]
            ],
            [
                [
                    219.301025390625,
                    275.8507385253906
                ],
                [
                    246.01602172851562,
                    292.9327392578125
                ]
            ],
            [
                [
                    249.26602172851562,
                    275.8507385253906
                ],
                [
                    316.41107177734375,
                    292.9327392578125
                ]
            ],
            [
                [
                    319.66107177734375,
                    275.8507385253906
                ],
                [
                    326.16107177734375,
                    292.9327392578125
                ]
            ],
            [
                [
                    329.41107177734375,
                    275.8507385253906
                ],
                [
                    373.4551086425781,
                    292.9327392578125
                ]
            ],
            [
                [
                    376.7051086425781,
                    275.8507385253906
                ],
                [
                    384.037109375,
                    292.9327392578125
                ]
            ],
            [
                [
                    387.287109375,
                    275.8507385253906
                ],
                [
                    431.3441467285156,
                    292.9327392578125
                ]
            ],
            [
                [
                    93.99401092529297,
                    291.45074462890625
                ],
                [
                    113.48101806640625,
                    308.5327453613281
                ]
            ],
            [
                [
                    116.73101806640625,
                    291.45074462890625
                ],
                [
                    133.3450164794922,
                    308.5327453613281
                ]
            ],
            [
                [
                    136.5950164794922,
                    291.45074462890625
                ],
                [
                    143.0950164794922,
                    308.5327453613281
                ]
            ],
            [
                [
                    145.62611389160156,
                    291.45074462890625
                ],
                [
                    179.32211303710938,
                    308.5327453613281
                ]
            ],
            [
                [
                    93.99401092529297,
                    307.0507507324219
                ],
                [
                    103.38001251220703,
                    324.13275146484375
                ]
            ],
            [
                [
                    106.63001251220703,
                    307.0507507324219
                ],
                [
                    123.24401092529297,
                    324.13275146484375
                ]
            ],
            [
                [
                    126.49401092529297,
                    307.0507507324219
                ],
                [
                    132.9940185546875,
                    324.13275146484375
                ]
            ],
            [
                [
                    136.2440185546875,
                    307.0507507324219
                ],
                [
                    159.84031677246094,
                    324.13275146484375
                ]
            ],
            [
                [
                    93.99401092529297,
                    322.6507568359375
                ],
                [
                    109.88001251220703,
                    339.7327575683594
                ]
            ],
            [
                [
                    113.13001251220703,
                    322.6507568359375
                ],
                [
                    129.7440185546875,
                    339.7327575683594
                ]
            ],
            [
                [
                    132.9940185546875,
                    322.6507568359375
                ],
                [
                    139.4940185546875,
                    339.7327575683594
                ]
            ],
            [
                [
                    142.7440185546875,
                    322.6507568359375
                ],
                [
                    172.84031677246094,
                    339.7327575683594
                ]
            ],
            [
                [
                    93.99401092529297,
                    338.2507629394531
                ],
                [
                    130.8360137939453,
                    355.332763671875
                ]
            ],
            [
                [
                    134.0860137939453,
                    338.2507629394531
                ],
                [
                    150.70001220703125,
                    355.332763671875
                ]
            ],
            [
                [
                    153.95001220703125,
                    338.2507629394531
                ],
                [
                    160.45001220703125,
                    355.332763671875
                ]
            ],
            [
                [
                    163.70001220703125,
                    338.2507629394531
                ],
                [
                    214.74710083007812,
                    355.332763671875
                ]
            ]
        ]
    },
    "4": {
        "text": "\u2022 Show the omission of letters (contraction) \u2013 positive I have \u2013 I\u2019ve I will \u2013 I\u2019ll I would \u2013 I\u2019d \u2022 Show the omission of letters (contraction) \u2013 negative + question Will not \u2013 Won\u2019t Cannot \u2013 Can\u2019t 2) \u2022 Show possession/ ownership e.g. :- Rahal\u2019s bat Abdul\u2019s book Ann\u2019s pencil Yoga\u2019s bicycle",
        "words": [
            "\u2022",
            "Show",
            "the",
            "omission",
            "of",
            "letters",
            "(contraction)",
            "\u2013",
            "positive",
            "I",
            "have",
            "\u2013",
            "I\u2019ve",
            "I",
            "will",
            "\u2013",
            "I\u2019ll",
            "I",
            "would",
            "\u2013",
            "I\u2019d",
            "\u2022",
            "Show",
            "the",
            "omission",
            "of",
            "letters",
            "(contraction)",
            "\u2013",
            "negative",
            "+",
            "question",
            "Will",
            "not",
            "\u2013",
            "Won\u2019t",
            "Cannot",
            "\u2013",
            "Can\u2019t",
            "2)",
            "\u2022",
            "Show",
            "possession/",
            "ownership",
            "e.g.",
            ":-",
            "Rahal\u2019s",
            "bat",
            "Abdul\u2019s",
            "book",
            "Ann\u2019s",
            "pencil",
            "Yoga\u2019s",
            "bicycle"
        ],
        "bounding_boxes": [
            [
                [
                    82.74900817871094,
                    359.85675048828125
                ],
                [
                    87.29901123046875,
                    376.9387512207031
                ]
            ],
            [
                [
                    93.99401092529297,
                    359.85675048828125
                ],
                [
                    123.60801696777344,
                    376.9387512207031
                ]
            ],
            [
                [
                    126.85801696777344,
                    359.85675048828125
                ],
                [
                    142.7440185546875,
                    376.9387512207031
                ]
            ],
            [
                [
                    145.9940185546875,
                    359.85675048828125
                ],
                [
                    192.9500274658203,
                    376.9387512207031
                ]
            ],
            [
                [
                    196.2000274658203,
                    359.85675048828125
                ],
                [
                    207.02902221679688,
                    376.9387512207031
                ]
            ],
            [
                [
                    210.27902221679688,
                    359.85675048828125
                ],
                [
                    242.051025390625,
                    376.9387512207031
                ]
            ],
            [
                [
                    245.301025390625,
                    359.85675048828125
                ],
                [
                    312.44610595703125,
                    376.9387512207031
                ]
            ],
            [
                [
                    315.69610595703125,
                    359.85675048828125
                ],
                [
                    322.19610595703125,
                    376.9387512207031
                ]
            ],
            [
                [
                    325.44610595703125,
                    359.85675048828125
                ],
                [
                    366.6171569824219,
                    376.9387512207031
                ]
            ],
            [
                [
                    93.99401092529297,
                    375.4567565917969
                ],
                [
                    98.32301330566406,
                    392.53875732421875
                ]
            ],
            [
                [
                    101.57301330566406,
                    375.4567565917969
                ],
                [
                    126.11701965332031,
                    392.53875732421875
                ]
            ],
            [
                [
                    129.3670196533203,
                    375.4567565917969
                ],
                [
                    135.8670196533203,
                    392.53875732421875
                ]
            ],
            [
                [
                    139.1170196533203,
                    375.4567565917969
                ],
                [
                    160.04701232910156,
                    392.53875732421875
                ]
            ],
            [
                [
                    93.99401092529297,
                    391.0567626953125
                ],
                [
                    98.32301330566406,
                    408.1387634277344
                ]
            ],
            [
                [
                    101.57301330566406,
                    391.0567626953125
                ],
                [
                    121.80101013183594,
                    408.1387634277344
                ]
            ],
            [
                [
                    125.05101013183594,
                    391.0567626953125
                ],
                [
                    131.55101013183594,
                    408.1387634277344
                ]
            ],
            [
                [
                    134.80101013183594,
                    391.0567626953125
                ],
                [
                    150.68699645996094,
                    408.1387634277344
                ]
            ],
            [
                [
                    93.99401092529297,
                    406.6567687988281
                ],
                [
                    98.32301330566406,
                    423.73876953125
                ]
            ],
            [
                [
                    101.57301330566406,
                    406.6567687988281
                ],
                [
                    134.07301330566406,
                    423.73876953125
                ]
            ],
            [
                [
                    137.32301330566406,
                    406.6567687988281
                ],
                [
                    143.82301330566406,
                    423.73876953125
                ]
            ],
            [
                [
                    147.07301330566406,
                    406.6567687988281
                ],
                [
                    162.2310028076172,
                    423.73876953125
                ]
            ],
            [
                [
                    82.74900817871094,
                    422.25677490234375
                ],
                [
                    87.29901123046875,
                    439.3387756347656
                ]
            ],
            [
                [
                    93.99401092529297,
                    422.25677490234375
                ],
                [
                    123.60801696777344,
                    439.3387756347656
                ]
            ],
            [
                [
                    126.85801696777344,
                    422.25677490234375
                ],
                [
                    142.7440185546875,
                    439.3387756347656
                ]
            ],
            [
                [
                    145.9940185546875,
                    422.25677490234375
                ],
                [
                    192.9500274658203,
                    439.3387756347656
                ]
            ],
            [
                [
                    196.2000274658203,
                    422.25677490234375
                ],
                [
                    207.02902221679688,
                    439.3387756347656
                ]
            ],
            [
                [
                    210.27902221679688,
                    422.25677490234375
                ],
                [
                    242.051025390625,
                    439.3387756347656
                ]
            ],
            [
                [
                    245.301025390625,
                    422.25677490234375
                ],
                [
                    312.44610595703125,
                    439.3387756347656
                ]
            ],
            [
                [
                    315.69610595703125,
                    422.25677490234375
                ],
                [
                    322.19610595703125,
                    439.3387756347656
                ]
            ],
            [
                [
                    325.44610595703125,
                    422.25677490234375
                ],
                [
                    369.4901428222656,
                    439.3387756347656
                ]
            ],
            [
                [
                    372.7401428222656,
                    422.25677490234375
                ],
                [
                    380.0721435546875,
                    439.3387756347656
                ]
            ],
            [
                [
                    383.3221435546875,
                    422.25677490234375
                ],
                [
                    427.3791809082031,
                    439.3387756347656
                ]
            ],
            [
                [
                    93.99401092529297,
                    437.8567810058594
                ],
                [
                    116.58541107177734,
                    454.93878173828125
                ]
            ],
            [
                [
                    119.83541107177734,
                    437.8567810058594
                ],
                [
                    136.4494171142578,
                    454.93878173828125
                ]
            ],
            [
                [
                    139.6994171142578,
                    437.8567810058594
                ],
                [
                    146.1994171142578,
                    454.93878173828125
                ]
            ],
            [
                [
                    149.20631408691406,
                    437.8567810058594
                ],
                [
                    181.14341735839844,
                    454.93878173828125
                ]
            ],
            [
                [
                    93.99401092529297,
                    453.456787109375
                ],
                [
                    131.55101013183594,
                    470.5387878417969
                ]
            ],
            [
                [
                    134.80101013183594,
                    453.456787109375
                ],
                [
                    141.30101013183594,
                    470.5387878417969
                ]
            ],
            [
                [
                    144.55101013183594,
                    453.456787109375
                ],
                [
                    173.19520568847656,
                    470.5387878417969
                ]
            ],
            [
                [
                    72.99900817871094,
                    479.05377197265625
                ],
                [
                    83.82801055908203,
                    496.1357727050781
                ]
            ],
            [
                [
                    87.07801055908203,
                    479.05377197265625
                ],
                [
                    91.62801361083984,
                    496.1357727050781
                ]
            ],
            [
                [
                    93.99401092529297,
                    479.05377197265625
                ],
                [
                    123.60801696777344,
                    496.1357727050781
                ]
            ],
            [
                [
                    130.10801696777344,
                    479.05377197265625
                ],
                [
                    189.33604431152344,
                    496.1357727050781
                ]
            ],
            [
                [
                    192.58604431152344,
                    479.05377197265625
                ],
                [
                    246.74404907226562,
                    496.1357727050781
                ]
            ],
            [
                [
                    72.99900817871094,
                    494.3288269042969
                ],
                [
                    91.77101135253906,
                    511.7358093261719
                ]
            ],
            [
                [
                    95.02101135253906,
                    494.3288269042969
                ],
                [
                    103.67901611328125,
                    511.7358093261719
                ]
            ],
            [
                [
                    108.99600982666016,
                    494.65380859375
                ],
                [
                    147.98822021484375,
                    511.7358093261719
                ]
            ],
            [
                [
                    151.23822021484375,
                    494.65380859375
                ],
                [
                    167.1242218017578,
                    511.7358093261719
                ]
            ],
            [
                [
                    108.99601745605469,
                    510.2537841796875
                ],
                [
                    150.16441345214844,
                    527.3358154296875
                ]
            ],
            [
                [
                    153.41441345214844,
                    510.2537841796875
                ],
                [
                    179.41441345214844,
                    527.3358154296875
                ]
            ],
            [
                [
                    108.99601745605469,
                    525.8538208007812
                ],
                [
                    140.0530242919922,
                    542.9358520507812
                ]
            ],
            [
                [
                    143.3030242919922,
                    525.8538208007812
                ],
                [
                    175.0750274658203,
                    542.9358520507812
                ]
            ],
            [
                [
                    108.99601745605469,
                    541.4537963867188
                ],
                [
                    144.5224151611328,
                    558.5358276367188
                ]
            ],
            [
                [
                    147.7724151611328,
                    541.4537963867188
                ],
                [
                    185.31642150878906,
                    558.5358276367188
                ]
            ]
        ]
    },
    "5": {
        "text": "\u2022 We don\u2019t use the apostrophe with the following possessive pronouns",
        "words": [
            "\u2022",
            "We",
            "don\u2019t",
            "use",
            "the",
            "apostrophe",
            "with",
            "the",
            "following",
            "possessive",
            "pronouns"
        ],
        "bounding_boxes": [
            [
                [
                    82.74901580810547,
                    564.0477905273438
                ],
                [
                    87.29901885986328,
                    581.1298217773438
                ]
            ],
            [
                [
                    94.9950180053711,
                    564.0477905273438
                ],
                [
                    111.99642181396484,
                    581.1298217773438
                ]
            ],
            [
                [
                    115.1853256225586,
                    564.0477905273438
                ],
                [
                    142.3930206298828,
                    581.1298217773438
                ]
            ],
            [
                [
                    145.58322143554688,
                    564.0477905273438
                ],
                [
                    162.9122314453125,
                    581.1298217773438
                ]
            ],
            [
                [
                    166.10243225097656,
                    564.0477905273438
                ],
                [
                    181.98843383789062,
                    581.1298217773438
                ]
            ],
            [
                [
                    185.17604064941406,
                    564.0477905273438
                ],
                [
                    242.2200469970703,
                    581.1298217773438
                ]
            ],
            [
                [
                    245.40895080566406,
                    564.0477905273438
                ],
                [
                    268.5229797363281,
                    581.1298217773438
                ]
            ],
            [
                [
                    271.7118835449219,
                    564.0477905273438
                ],
                [
                    287.597900390625,
                    581.1298217773438
                ]
            ],
            [
                [
                    290.7854919433594,
                    564.0477905273438
                ],
                [
                    341.342529296875,
                    581.1298217773438
                ]
            ],
            [
                [
                    344.5340270996094,
                    564.0477905273438
                ],
                [
                    399.4200744628906,
                    581.1298217773438
                ]
            ],
            [
                [
                    402.6141662597656,
                    564.0477905273438
                ],
                [
                    451.00018310546875,
                    581.1298217773438
                ]
            ]
        ]
    },
    "6": {
        "text": "Yours His Hers Ours Theirs Its ( belonging to it)",
        "words": [
            "Yours",
            "His",
            "Hers",
            "Ours",
            "Theirs",
            "Its",
            "(",
            "belonging",
            "to",
            "it)"
        ],
        "bounding_boxes": [
            [
                [
                    95.99601745605469,
                    579.6478271484375
                ],
                [
                    126.46932220458984,
                    596.7298583984375
                ]
            ],
            [
                [
                    217.00001525878906,
                    579.6478271484375
                ],
                [
                    235.05702209472656,
                    596.7298583984375
                ]
            ],
            [
                [
                    325.0040283203125,
                    579.6478271484375
                ],
                [
                    349.54803466796875,
                    596.7298583984375
                ]
            ],
            [
                [
                    97.99803161621094,
                    595.247802734375
                ],
                [
                    123.27003479003906,
                    612.329833984375
                ]
            ],
            [
                [
                    217.00003051757812,
                    595.247802734375
                ],
                [
                    250.21502685546875,
                    612.329833984375
                ]
            ],
            [
                [
                    325.0040283203125,
                    595.247802734375
                ],
                [
                    338.0040588378906,
                    612.329833984375
                ]
            ],
            [
                [
                    341.2540588378906,
                    595.247802734375
                ],
                [
                    345.58306884765625,
                    612.329833984375
                ]
            ],
            [
                [
                    348.83306884765625,
                    595.247802734375
                ],
                [
                    400.8330993652344,
                    612.329833984375
                ]
            ],
            [
                [
                    404.0830993652344,
                    595.247802734375
                ],
                [
                    414.1971130371094,
                    612.329833984375
                ]
            ],
            [
                [
                    417.4471130371094,
                    595.247802734375
                ],
                [
                    429.004150390625,
                    612.329833984375
                ]
            ]
        ]
    }
}